.DS_Store
topaz/__init__.py
topaz/fortran.py
topaz/history.py
topaz/plot.py
topaz/weight.py
topaz-0.0.3.dist-info/METADATA
topaz-0.0.3.dist-info/RECORD
topaz-0.0.3.dist-info/WHEEL
topaz-0.0.3.dist-info/top_level.txt
