Metadata-Version: 2.1
Name: topaz
Version: 0.0.3
Summary: A plotting package for the Aurora simulations using pynbody
Home-page: https://github.com/abatten/topaz
Author: Adam Batten
Author-email: adamjbatten@gmail.com
License: UNKNOWN
Platform: UNKNOWN
Classifier: Programming Language :: Python :: 3
Classifier: License :: OSI Approved :: MIT License
Classifier: Operating System :: OS Independent
